roverqaz_simple_api/__init__.py
roverqaz_simple_api/__main__.py
roverqaz_simple_api/app.py
roverqaz_simple_api-0.1.9.dist-info/METADATA
roverqaz_simple_api-0.1.9.dist-info/WHEEL
roverqaz_simple_api-0.1.9.dist-info/top_level.txt
roverqaz_simple_api-0.1.9.dist-info/RECORD
