Metadata-Version: 2.1
Name: roverqaz-simple-api
Version: 0.1.9
Summary: A simple api package
Home-page: https://gitlab.com/roverqaz/test-task-python
Author: Adil Idrissov
Author-email: idrissov.adil@gmail.com
License: UNKNOWN
Platform: UNKNOWN
Classifier: Programming Language :: Python :: 3
Classifier: License :: OSI Approved :: MIT License
Classifier: Operating System :: OS Independent
Requires-Python: >=3.6
Requires-Dist: flask
Requires-Dist: psycopg2-binary
Requires-Dist: flask-sqlalchemy
